urdf_to_usd/__init__.py
urdf_to_usd/convert.py
urdf_to_usd/py.typed
urdf_to_usd-0.1.0.dist-info/METADATA
urdf_to_usd-0.1.0.dist-info/WHEEL
urdf_to_usd-0.1.0.dist-info/RECORD
